<?xml version="1.0" encoding="UTF-8"?>
<?xml-stylesheet type="text/xsl" href="../xsl/codeSystem2html.xsl"?>
<?oxygen SCHSchema="vocab.sch"?>
<codeSystem xmlns:xsi="http://www.w3.org/2001/XMLSchema-instance" xsi:schemaLocation="urn:hl7-org:v3 vocab.xsd" xmlns="urn:hl7-org:v3">
    <name>EducationLevel</name>
    <desc>Opleidingsniveau</desc>
    <code code="ASSOC" codeSystem="2.16.840.1.113883.5.1077" displayName="Associate's or technical degree complete">
        <originalText/>
    </code>
    <code code="BD" codeSystem="2.16.840.1.113883.5.1077" displayName="College or baccalaureate degree complete">
        <originalText>HBO voltooid</originalText>
    </code>
    <code code="ELEM" codeSystem="2.16.840.1.113883.5.1077" displayName="Elementary School">
        <originalText>basisschool (lagere school)</originalText>
    </code>
    <code code="GD" codeSystem="2.16.840.1.113883.5.1077" displayName="Graduate or professional Degree complete">
        <originalText>universiteit voltooid (is dit incl. hogeschool?)</originalText>
    </code>
    <code code="HS" codeSystem="2.16.840.1.113883.5.1077" displayName="High School or secondary school degree complete">
        <originalText>middelbare school voltooid</originalText>
    </code>
    <code code="PB" codeSystem="2.16.840.1.113883.5.1077" displayName="Some post-baccalaureate education">
        <originalText>universiteit niet voltooid (aansluitend op HBO)</originalText>
    </code>
    <code code="POSTG" codeSystem="2.16.840.1.113883.5.1077" displayName="Doctoral or post graduate education">
        <originalText>post-doctoraal</originalText>
    </code>
    <code code="SCOL" codeSystem="2.16.840.1.113883.5.1077" displayName="Some College education">
        <originalText>HBO niet voltooid</originalText>
    </code>
    <code code="SEC" codeSystem="2.16.840.1.113883.5.1077" displayName="Some secondary or high school education">
        <originalText>middelbare school niet voltooid</originalText>
    </code>
</codeSystem>
